brcode/__init__.py
brcode/crc.py
python_brcode-0.2.0.dist-info/METADATA
python_brcode-0.2.0.dist-info/WHEEL
python_brcode-0.2.0.dist-info/RECORD
