Metadata-Version: 2.1
Name: python-brcode
Version: 0.2.0
Summary: Generates static BR Codes that could be used for PIX payments using simple value copy and paste or generating QR Codes.
Home-page: https://github.com/victor-torres/python-brcode
Author: Victor Torres
Author-email: vpaivatorres@gmail.com
Requires-Python: >=3.10,<4.0
Classifier: Programming Language :: Python :: 3
Classifier: Programming Language :: Python :: 3.10
Classifier: Programming Language :: Python :: 3.11
